LICENSE
MANIFEST.in
README.md
package.json
setup.py
dash_mp_components/BibCard.py
dash_mp_components/BibFilter.py
dash_mp_components/BibjsonCard.py
dash_mp_components/BibjsonFilter.py
dash_mp_components/BibtexButton.py
dash_mp_components/CameraContextProvider.py
dash_mp_components/CrossrefCard.py
dash_mp_components/CrystalToolkitScene.py
dash_mp_components/DataBlock.py
dash_mp_components/DataTable.py
dash_mp_components/Download.py
dash_mp_components/DownloadButton.py
dash_mp_components/DownloadDropdown.py
dash_mp_components/Drawer.py
dash_mp_components/DrawerContextProvider.py
dash_mp_components/DrawerTrigger.py
dash_mp_components/Dropdown.py
dash_mp_components/DualRangeSlider.py
dash_mp_components/Enlargeable.py
dash_mp_components/FilterField.py
dash_mp_components/Formula.py
dash_mp_components/GlobalSearchBar.py
dash_mp_components/GraphComponent.py
dash_mp_components/JsonView.py
dash_mp_components/Link.py
dash_mp_components/Markdown.py
dash_mp_components/MatSidebar.py
dash_mp_components/MaterialsInput.py
dash_mp_components/Modal.py
dash_mp_components/ModalContextProvider.py
dash_mp_components/ModalTrigger.py
dash_mp_components/Navbar.py
dash_mp_components/NavbarDropdown.py
dash_mp_components/NotificationDropdown.py
dash_mp_components/OpenAccessButton.py
dash_mp_components/OpenAccessLink.py
dash_mp_components/PeriodicContext.py
dash_mp_components/PeriodicContextTable.py
dash_mp_components/PeriodicElement.py
dash_mp_components/PeriodicFilter.py
dash_mp_components/PeriodicTableInput.py
dash_mp_components/PublicationButton.py
dash_mp_components/RangeSlider.py
dash_mp_components/Scrollspy.py
dash_mp_components/SearchUI.py
dash_mp_components/SearchUIContainer.py
dash_mp_components/SearchUIDataHeader.py
dash_mp_components/SearchUIDataView.py
dash_mp_components/SearchUIFilters.py
dash_mp_components/SearchUIGrid.py
dash_mp_components/SearchUISearchBar.py
dash_mp_components/Select.py
dash_mp_components/Switch.py
dash_mp_components/SynthesisRecipeCard.py
dash_mp_components.egg-info/PKG-INFO
dash_mp_components.egg-info/SOURCES.txt
dash_mp_components.egg-info/dependency_links.txt
dash_mp_components.egg-info/top_level.txt