Metadata-Version: 1.1
Name: dash-mp-components
Version: 0.4.39
Summary: Dash components for the Materials Project
Home-page: UNKNOWN
Author: Materials Project Team <feedback@materialsproject.org>
Author-email: UNKNOWN
License: BSD
Platform: UNKNOWN
Classifier: Framework :: Dash
